configlib/__init__.py
configlib/configlib.py
tests/__init__.py
tests/test_configlib.py
configlib-2.0.4.dist-info/LICENSE
configlib-2.0.4.dist-info/METADATA
configlib-2.0.4.dist-info/WHEEL
configlib-2.0.4.dist-info/top_level.txt
configlib-2.0.4.dist-info/RECORD
