Metadata-Version: 2.1
Name: configlib
Version: 2.0.4
Summary: wrapper for ConfigParser allowing for simple get calls to set options.
Home-page: https://github.com/jeffbryner/configlib
Author: Jeff Bryner
Author-email: jeff@jeffbryner.com
License: UNKNOWN
Platform: UNKNOWN
Classifier: Programming Language :: Python :: 2
Classifier: Programming Language :: Python :: 3
Classifier: Operating System :: OS Independent
Classifier: License :: OSI Approved :: Mozilla Public License 2.0 (MPL 2.0)
Requires-Dist: everett (==0.9)
